PathSelector/__init__.py
PathSelector/selector.py
PathSelector-0.1.4.dist-info/METADATA
PathSelector-0.1.4.dist-info/WHEEL
PathSelector-0.1.4.dist-info/top_level.txt
PathSelector-0.1.4.dist-info/RECORD
