Metadata-Version: 2.1
Name: PathSelector
Version: 0.1.4
Summary: PathSelector is a simple path selection module for python.
Home-page: https://github.com/mozancetin/PathSelector
Author: Mustafa Ozan Çetin
Author-email: 
License: MIT
Keywords: python,path,selector,file,directory
Platform: UNKNOWN
Classifier: Development Status :: 3 - Alpha
Classifier: Intended Audience :: Developers
Classifier: License :: OSI Approved :: MIT License
Classifier: Programming Language :: Python :: 3
Classifier: Topic :: Software Development :: Libraries :: Python Modules
